<?xml version="1.0" encoding="UTF-8"?>
<tables>
    <BCME3410_row>
        <mh_itemserialno1/>
        <mh_itemserialno2/>
        <mh_itemserialno3/>
        <mh_itemserialno4/>
        <budgetno/>
        <mh_budgetname>合         計</mh_budgetname>
        <budgetno_conver/>
        <tyear_amt>97719.000000</tyear_amt>
        <lyear_amt>151389.000000</lyear_amt>
        <byear_amt>146100.000000</byear_amt>
        <b_amt>-53670.000000</b_amt>
        <bc_content/>
        <blevel>9</blevel>
        <ordinaryid>1</ordinaryid>
    </BCME3410_row>
    <BCME3410_row>
        <mh_itemserialno1>2</mh_itemserialno1>
        <mh_itemserialno2/>
        <mh_itemserialno3/>
        <mh_itemserialno4/>
        <budgetno>04000000000</budgetno>
        <mh_budgetname>罰款及賠償收入</mh_budgetname>
        <budgetno_conver>0400000000</budgetno_conver>
        <tyear_amt>8000.000000</tyear_amt>
        <lyear_amt>8000.000000</lyear_amt>
        <byear_amt>3629.000000</byear_amt>
        <b_amt>0.000000</b_amt>
        <bc_content/>
        <blevel>1</blevel>
        <ordinaryid/>
    </BCME3410_row>
    <BCME3410_row>
        <mh_itemserialno1/>
        <mh_itemserialno2>190</mh_itemserialno2>
        <mh_itemserialno3/>
        <mh_itemserialno4/>
        <budgetno>04610010000</budgetno>
        <mh_budgetname>文化部</mh_budgetname>
        <budgetno_conver>0461010000</budgetno_conver>
        <tyear_amt>8000.000000</tyear_amt>
        <lyear_amt>8000.000000</lyear_amt>
        <byear_amt>3629.000000</byear_amt>
        <b_amt>0.000000</b_amt>
        <bc_content/>
        <blevel>2</blevel>
        <ordinaryid/>
    </BCME3410_row>
    <BCME3410_row>
        <mh_itemserialno1/>
        <mh_itemserialno2/>
        <mh_itemserialno3>01</mh_itemserialno3>
        <mh_itemserialno4/>
        <budgetno>04610010100</budgetno>
        <mh_budgetname>罰金罰鍰及怠金</mh_budgetname>
        <budgetno_conver>0461010100</budgetno_conver>
        <tyear_amt>0.000000</tyear_amt>
        <lyear_amt>0.000000</lyear_amt>
        <byear_amt>40.000000</byear_amt>
        <b_amt>0.000000</b_amt>
        <bc_content/>
        <blevel>3</blevel>
        <ordinaryid/>
    </BCME3410_row>
    <BCME3410_row>
        <mh_itemserialno1/>
        <mh_itemserialno2/>
        <mh_itemserialno3/>
        <mh_itemserialno4>01</mh_itemserialno4>
        <budgetno>04610010101</budgetno>
        <mh_budgetname>罰金罰鍰</mh_budgetname>
        <budgetno_conver>0461010101</budgetno_conver>
        <tyear_amt>0.000000</tyear_amt>
        <lyear_amt>0.000000</lyear_amt>
        <byear_amt>40.000000</byear_amt>
        <b_amt>0.000000</b_amt>
        <bc_key>04610010101xxxxxxxxxxxxxxxxxxxxxxxx1R1x0</bc_key>
        <bc_content>前年度決算數係未經許可發行大
陸地區雜誌之罰鍰收入。</bc_content>
        <blevel>4</blevel>
        <ordinaryid/>
    </BCME3410_row>
    <BCME3410_row>
        <mh_itemserialno1/>
        <mh_itemserialno2/>
        <mh_itemserialno3>02</mh_itemserialno3>
        <mh_itemserialno4/>
        <budgetno>04610010300</budgetno>
        <mh_budgetname>賠償收入</mh_budgetname>
        <budgetno_conver>0461010300</budgetno_conver>
        <tyear_amt>8000.000000</tyear_amt>
        <lyear_amt>8000.000000</lyear_amt>
        <byear_amt>3589.000000</byear_amt>
        <b_amt>0.000000</b_amt>
        <bc_content/>
        <blevel>3</blevel>
        <ordinaryid/>
    </BCME3410_row>
    <BCME3410_row>
        <mh_itemserialno1/>
        <mh_itemserialno2/>
        <mh_itemserialno3/>
        <mh_itemserialno4>01</mh_itemserialno4>
        <budgetno>04610010301</budgetno>
        <mh_budgetname>一般賠償收入</mh_budgetname>
        <budgetno_conver>0461010301</budgetno_conver>
        <tyear_amt>8000.000000</tyear_amt>
        <lyear_amt>8000.000000</lyear_amt>
        <byear_amt>3589.000000</byear_amt>
        <b_amt>0.000000</b_amt>
        <bc_key>04610010301xxxxxxxxxxxxxxxxxxxxxxxx1R1x0</bc_key>
        <bc_content>本年度預算數係廠商違約逾期交
貨之賠償收入。</bc_content>
        <blevel>4</blevel>
        <ordinaryid/>
    </BCME3410_row>
    <BCME3410_row>
        <mh_itemserialno1>3</mh_itemserialno1>
        <mh_itemserialno2/>
        <mh_itemserialno3/>
        <mh_itemserialno4/>
        <budgetno>05000000000</budgetno>
        <mh_budgetname>規費收入</mh_budgetname>
        <budgetno_conver>0500000000</budgetno_conver>
        <tyear_amt>12150.000000</tyear_amt>
        <lyear_amt>12080.000000</lyear_amt>
        <byear_amt>12124.000000</byear_amt>
        <b_amt>70.000000</b_amt>
        <bc_content/>
        <blevel>1</blevel>
        <ordinaryid/>
    </BCME3410_row>
    <BCME3410_row>
        <mh_itemserialno1/>
        <mh_itemserialno2>160</mh_itemserialno2>
        <mh_itemserialno3/>
        <mh_itemserialno4/>
        <budgetno>05610010000</budgetno>
        <mh_budgetname>文化部</mh_budgetname>
        <budgetno_conver>0561010000</budgetno_conver>
        <tyear_amt>12150.000000</tyear_amt>
        <lyear_amt>12080.000000</lyear_amt>
        <byear_amt>12124.000000</byear_amt>
        <b_amt>70.000000</b_amt>
        <bc_content/>
        <blevel>2</blevel>
        <ordinaryid/>
    </BCME3410_row>
    <BCME3410_row>
        <mh_itemserialno1/>
        <mh_itemserialno2/>
        <mh_itemserialno3>01</mh_itemserialno3>
        <mh_itemserialno4/>
        <budgetno>05610010100</budgetno>
        <mh_budgetname>行政規費收入</mh_budgetname>
        <budgetno_conver>0561010100</budgetno_conver>
        <tyear_amt>20.000000</tyear_amt>
        <lyear_amt>20.000000</lyear_amt>
        <byear_amt>22.000000</byear_amt>
        <b_amt>0.000000</b_amt>
        <bc_content/>
        <blevel>3</blevel>
        <ordinaryid/>
    </BCME3410_row>
    <BCME3410_row>
        <mh_itemserialno1/>
        <mh_itemserialno2/>
        <mh_itemserialno3/>
        <mh_itemserialno4>01</mh_itemserialno4>
        <budgetno>05610010101</budgetno>
        <mh_budgetname>審查費</mh_budgetname>
        <budgetno_conver>0561010101</budgetno_conver>
        <tyear_amt>20.000000</tyear_amt>
        <lyear_amt>20.000000</lyear_amt>
        <byear_amt>22.000000</byear_amt>
        <b_amt>0.000000</b_amt>
        <bc_key>05610010101xxxxxxxxxxxxxxxxxxxxxxxx1R1x0</bc_key>
        <bc_content>本年度預算數係大陸地區暨香港
澳門出版品在臺銷售發行之審查
費收入。</bc_content>
        <blevel>4</blevel>
        <ordinaryid/>
    </BCME3410_row>
    <BCME3410_row>
        <mh_itemserialno1/>
        <mh_itemserialno2/>
        <mh_itemserialno3>02</mh_itemserialno3>
        <mh_itemserialno4/>
        <budgetno>05610010300</budgetno>
        <mh_budgetname>使用規費收入</mh_budgetname>
        <budgetno_conver>0561010300</budgetno_conver>
        <tyear_amt>12130.000000</tyear_amt>
        <lyear_amt>12060.000000</lyear_amt>
        <byear_amt>12101.000000</byear_amt>
        <b_amt>70.000000</b_amt>
        <bc_content/>
        <blevel>3</blevel>
        <ordinaryid/>
    </BCME3410_row>
    <BCME3410_row>
        <mh_itemserialno1/>
        <mh_itemserialno2/>
        <mh_itemserialno3/>
        <mh_itemserialno4>01</mh_itemserialno4>
        <budgetno>05610010305</budgetno>
        <mh_budgetname>資料使用費</mh_budgetname>
        <budgetno_conver>0561010305</budgetno_conver>
        <tyear_amt>100.000000</tyear_amt>
        <lyear_amt>100.000000</lyear_amt>
        <byear_amt>815.000000</byear_amt>
        <b_amt>0.000000</b_amt>
        <bc_key>05610010305xxxxxxxxxxxxxxxxxxxxxxxx1R1x0</bc_key>
        <bc_content>本年度預算數係國立臺灣歷史博
物館典藏品圖像影音資料使用費
收入。</bc_content>
        <blevel>4</blevel>
        <ordinaryid/>
    </BCME3410_row>
    <BCME3410_row>
        <mh_itemserialno1/>
        <mh_itemserialno2/>
        <mh_itemserialno3/>
        <mh_itemserialno4>02</mh_itemserialno4>
        <budgetno>05610010312</budgetno>
        <mh_budgetname>場地設施使用費</mh_budgetname>
        <budgetno_conver>0561010312</budgetno_conver>
        <tyear_amt>12030.000000</tyear_amt>
        <lyear_amt>11960.000000</lyear_amt>
        <byear_amt>11286.000000</byear_amt>
        <b_amt>70.000000</b_amt>
        <bc_key>05610010312xxxxxxxxxxxxxxxxxxxxxxxx1R1x0</bc_key>
        <bc_content>本年度預算數之內容與上年度之
比較如下：
1.國立臺灣歷史博物館門票收入
　11,200千元，與上年度同，其
　中5,000千元撥充作為展示教
　育大樓保全、清潔及服務人力
　等經費之用。
2.國立臺灣文學館及齊東詩舍場
　地出借收入172千元，較上年
　度增列12千元。
3.國立臺灣交響樂團演奏廳場地
　出借收入658千元，較上年度
　增列58千元。</bc_content>
        <blevel>4</blevel>
        <ordinaryid/>
    </BCME3410_row>
    <BCME3410_row>
        <mh_itemserialno1>4</mh_itemserialno1>
        <mh_itemserialno2/>
        <mh_itemserialno3/>
        <mh_itemserialno4/>
        <budgetno>07000000000</budgetno>
        <mh_budgetname>財產收入</mh_budgetname>
        <budgetno_conver>0700000000</budgetno_conver>
        <tyear_amt>54249.000000</tyear_amt>
        <lyear_amt>53674.000000</lyear_amt>
        <byear_amt>68375.000000</byear_amt>
        <b_amt>575.000000</b_amt>
        <bc_content/>
        <blevel>1</blevel>
        <ordinaryid/>
    </BCME3410_row>
    <BCME3410_row>
        <mh_itemserialno1/>
        <mh_itemserialno2>206</mh_itemserialno2>
        <mh_itemserialno3/>
        <mh_itemserialno4/>
        <budgetno>07610010000</budgetno>
        <mh_budgetname>文化部</mh_budgetname>
        <budgetno_conver>0761010000</budgetno_conver>
        <tyear_amt>54249.000000</tyear_amt>
        <lyear_amt>53674.000000</lyear_amt>
        <byear_amt>68375.000000</byear_amt>
        <b_amt>575.000000</b_amt>
        <bc_content/>
        <blevel>2</blevel>
        <ordinaryid/>
    </BCME3410_row>
    <BCME3410_row>
        <mh_itemserialno1/>
        <mh_itemserialno2/>
        <mh_itemserialno3>01</mh_itemserialno3>
        <mh_itemserialno4/>
        <budgetno>07610010100</budgetno>
        <mh_budgetname>財產孳息</mh_budgetname>
        <budgetno_conver>0761010100</budgetno_conver>
        <tyear_amt>54209.000000</tyear_amt>
        <lyear_amt>53581.000000</lyear_amt>
        <byear_amt>68310.000000</byear_amt>
        <b_amt>628.000000</b_amt>
        <bc_content/>
        <blevel>3</blevel>
        <ordinaryid/>
    </BCME3410_row>
    <BCME3410_row>
        <mh_itemserialno1/>
        <mh_itemserialno2/>
        <mh_itemserialno3/>
        <mh_itemserialno4>01</mh_itemserialno4>
        <budgetno>07610010101</budgetno>
        <mh_budgetname>利息收入</mh_budgetname>
        <budgetno_conver>0761010101</budgetno_conver>
        <tyear_amt>0.000000</tyear_amt>
        <lyear_amt>0.000000</lyear_amt>
        <byear_amt>217.000000</byear_amt>
        <b_amt>0.000000</b_amt>
        <bc_key>07610010101xxxxxxxxxxxxxxxxxxxxxxxx1R1x0</bc_key>
        <bc_content>前年度決算數係專戶存款等利息
收入。</bc_content>
        <blevel>4</blevel>
        <ordinaryid/>
    </BCME3410_row>
    <BCME3410_row>
        <mh_itemserialno1/>
        <mh_itemserialno2/>
        <mh_itemserialno3/>
        <mh_itemserialno4>02</mh_itemserialno4>
        <budgetno>07610010105</budgetno>
        <mh_budgetname>權利金</mh_budgetname>
        <budgetno_conver>0761010105</budgetno_conver>
        <tyear_amt>17657.000000</tyear_amt>
        <lyear_amt>18708.000000</lyear_amt>
        <byear_amt>33171.000000</byear_amt>
        <b_amt>-1051.000000</b_amt>
        <bc_key>07610010105xxxxxxxxxxxxxxxxxxxxxxxx1R1x0</bc_key>
        <bc_content>本年度預算數之內容與上年度之
比較如下：
1.文化創意產業園區委外經營權
　利金收入7,903千元，較上年
　度減列1,051千元。
2.新北市板橋區新板特區特專三
　臨時停車場委外經營權利金收
　入5,769千元，與上年度同。
3.文化部影像資料授權權利金收
　入300千元，與上年度同。
4.國立臺灣文學館文物圖像授權
　權利金收入20千元，與上年度
　同。
5.國立臺灣歷史博物館場地委外
　經營權利金收入1,150千元，
　與上年度同，其中150千元撥
　充作為停車場清潔等經費之用
　。
6.國立臺灣交響樂團場地委外經
　營權利金收入2,515千元，與
　上年度同。</bc_content>
        <blevel>4</blevel>
        <ordinaryid/>
    </BCME3410_row>
    <BCME3410_row>
        <mh_itemserialno1/>
        <mh_itemserialno2/>
        <mh_itemserialno3/>
        <mh_itemserialno4>03</mh_itemserialno4>
        <budgetno>07610010106</budgetno>
        <mh_budgetname>租金收入</mh_budgetname>
        <budgetno_conver>0761010106</budgetno_conver>
        <tyear_amt>36552.000000</tyear_amt>
        <lyear_amt>34873.000000</lyear_amt>
        <byear_amt>34922.000000</byear_amt>
        <b_amt>1679.000000</b_amt>
        <bc_key>07610010106xxxxxxxxxxxxxxxxxxxxxxxx1R1x0</bc_key>
        <bc_content>本年度預算數之內容與上年度之
比較如下：
1.文化創意產業園區土地及房屋
　租金收入32,614千元，較上年
　度增列559千元。
2.藝術銀行藝術品出租收入2,10
　0千元，較上年度增列1,120千
　元，其中1,100千元撥充作為
　藝術銀行之管理維護等經費之
　用。
3.火炎山傳輸平臺場地租金收入
　1,170千元，與上年度同。
4.國立臺灣文學館及齊東詩舍場
　地租金收入548千元，與上年
　度同。
5.國立臺灣歷史博物館商店場地
　租金收入40千元，與上年度同
　。
6.國立臺灣交響樂團土地租金收
　入80千元，與上年度同。</bc_content>
        <blevel>4</blevel>
        <ordinaryid/>
    </BCME3410_row>
    <BCME3410_row>
        <mh_itemserialno1/>
        <mh_itemserialno2/>
        <mh_itemserialno3>02</mh_itemserialno3>
        <mh_itemserialno4/>
        <budgetno>07610010600</budgetno>
        <mh_budgetname>廢舊物資售價</mh_budgetname>
        <budgetno_conver>0761010600</budgetno_conver>
        <tyear_amt>40.000000</tyear_amt>
        <lyear_amt>93.000000</lyear_amt>
        <byear_amt>66.000000</byear_amt>
        <b_amt>-53.000000</b_amt>
        <bc_key>07610010600xxxxxxxxxxxxxxxxxxxxxxxx1R1x0</bc_key>
        <bc_content>本年度預算數係出售報廢財物及
廢紙等收入。</bc_content>
        <blevel>3</blevel>
        <ordinaryid/>
    </BCME3410_row>
    <BCME3410_row>
        <mh_itemserialno1>7</mh_itemserialno1>
        <mh_itemserialno2/>
        <mh_itemserialno3/>
        <mh_itemserialno4/>
        <budgetno>11000000000</budgetno>
        <mh_budgetname>其他收入</mh_budgetname>
        <budgetno_conver>1100000000</budgetno_conver>
        <tyear_amt>23320.000000</tyear_amt>
        <lyear_amt>77635.000000</lyear_amt>
        <byear_amt>61972.000000</byear_amt>
        <b_amt>-54315.000000</b_amt>
        <bc_content/>
        <blevel>1</blevel>
        <ordinaryid/>
    </BCME3410_row>
    <BCME3410_row>
        <mh_itemserialno1/>
        <mh_itemserialno2>200</mh_itemserialno2>
        <mh_itemserialno3/>
        <mh_itemserialno4/>
        <budgetno>11610010000</budgetno>
        <mh_budgetname>文化部</mh_budgetname>
        <budgetno_conver>1161010000</budgetno_conver>
        <tyear_amt>23320.000000</tyear_amt>
        <lyear_amt>77635.000000</lyear_amt>
        <byear_amt>61972.000000</byear_amt>
        <b_amt>-54315.000000</b_amt>
        <bc_content/>
        <blevel>2</blevel>
        <ordinaryid/>
    </BCME3410_row>
    <BCME3410_row>
        <mh_itemserialno1/>
        <mh_itemserialno2/>
        <mh_itemserialno3>01</mh_itemserialno3>
        <mh_itemserialno4/>
        <budgetno>11610010900</budgetno>
        <mh_budgetname>雜項收入</mh_budgetname>
        <budgetno_conver>1161010900</budgetno_conver>
        <tyear_amt>23320.000000</tyear_amt>
        <lyear_amt>77635.000000</lyear_amt>
        <byear_amt>61972.000000</byear_amt>
        <b_amt>-54315.000000</b_amt>
        <bc_content/>
        <blevel>3</blevel>
        <ordinaryid/>
    </BCME3410_row>
    <BCME3410_row>
        <mh_itemserialno1/>
        <mh_itemserialno2/>
        <mh_itemserialno3/>
        <mh_itemserialno4>01</mh_itemserialno4>
        <budgetno>11610010901</budgetno>
        <mh_budgetname>收回以前年度歲出</mh_budgetname>
        <budgetno_conver>1161010901</budgetno_conver>
        <tyear_amt>9120.000000</tyear_amt>
        <lyear_amt>63037.000000</lyear_amt>
        <byear_amt>46486.000000</byear_amt>
        <b_amt>-53917.000000</b_amt>
        <bc_key>11610010901xxxxxxxxxxxxxxxxxxxxxxxx1R1x0</bc_key>
        <bc_content>本年度預算數係收回新生報業公
司員工勞保補償金等繳庫數。</bc_content>
        <blevel>4</blevel>
        <ordinaryid/>
    </BCME3410_row>
    <BCME3410_row>
        <mh_itemserialno1/>
        <mh_itemserialno2/>
        <mh_itemserialno3/>
        <mh_itemserialno4>02</mh_itemserialno4>
        <budgetno>11610010909</budgetno>
        <mh_budgetname>其他雜項收入</mh_budgetname>
        <budgetno_conver>1161010909</budgetno_conver>
        <tyear_amt>14200.000000</tyear_amt>
        <lyear_amt>14598.000000</lyear_amt>
        <byear_amt>15486.000000</byear_amt>
        <b_amt>-398.000000</b_amt>
        <bc_key>11610010909xxxxxxxxxxxxxxxxxxxxxxxx1R1x0</bc_key>
        <bc_content>本年度預算數之內容與上年度之
比較如下：
1.國立臺灣文學館辦理臺灣文學
　教室、青少年文學編輯營及文
　學踏查報名費收入184千元，
　與上年度同，全數撥充作為鐘
　點費及印刷等經費之用。
2.國立臺灣交響樂團辦理各項音
　樂營及研習活動報名費等收入
　1,500千元，與上年度同，全
　數撥充作為講師鐘點費、演出
　費、音樂家與學員膳宿費、交
　通費及文宣品印刷等經費之用
　。
3.國立臺灣交響樂團演出活動門
　票收入7,400千元，與上年度
　同。
4.國立臺灣交響樂團受邀演出收
　入1,856千元，與上年度同。
5.文化部、國立臺灣文學館、國
　立臺灣歷史博物館、國立臺灣
　交響樂團出售出版品等收入3,
　081千元，與上年度同。
6.文化部借用宿舍員工自薪資扣
　回繳庫數35千元，與上年度同
　。
7.文化部停車場使用費等收入14
　4千元，較上年度減列48千元
　。
8.上年度衛武營藝術文化中心籌
　備處演出活動等收入350千元
　，本年度不再編列，如數減列
　。</bc_content>
        <blevel>4</blevel>
        <ordinaryid/>
    </BCME3410_row>
</tables>
